calysto_lc3/__init__.py
calysto_lc3/__main__.py
calysto_lc3/_version.py
calysto_lc3/install.py
calysto_lc3/kernel.py
calysto_lc3/lc3.py
calysto_lc3/images/logo-32x32.png
calysto_lc3/images/logo-64x64.png
calysto_lc3-0.6.dist-info/DESCRIPTION.rst
calysto_lc3-0.6.dist-info/METADATA
calysto_lc3-0.6.dist-info/RECORD
calysto_lc3-0.6.dist-info/WHEEL
calysto_lc3-0.6.dist-info/metadata.json
calysto_lc3-0.6.dist-info/top_level.txt
