Metadata-Version: 2.0
Name: calysto-lc3
Version: 0.6
Summary: An LC-3 Assembly Language kernel for Jupyter based on MetaKernel
Home-page: https://github.com/Calysto/calysto_lc3
Author: Douglas Blank
Author-email: doug.blank@gmail.com
License: UNKNOWN
Platform: UNKNOWN
Classifier: Framework :: IPython
Classifier: License :: OSI Approved :: BSD License
Classifier: Programming Language :: Python :: 3
Classifier: Programming Language :: Python :: 2
Classifier: Programming Language :: Lisp
Classifier: Topic :: System :: Shells
Requires-Dist: metakernel
